{
    "jogadores": [
        {
            "nome": "Lionel Messi",
            "pais": "Argentina",
            "bandeira": "🇦🇷",
            "idade": 38,
            "posicao": "Atacante",
            "principalClube": "Barcelona",
            "clubeAtual": "Inter Miami",
            "titulos": ["Copa do Mundo", "8x Bola de Ouro", "4x Champions League", "10x La Liga"],
            "curiosidade": "Maior artilheiro da história do Barcelona"
        },
        {
            "nome": "Cristiano Ronaldo",
            "pais": "Portugal",
            "bandeira": "🇵🇹",
            "idade": 41,
            "posicao": "Atacante",
            "principalClube": "Real Madrid",
            "clubeAtual": "Al-Nassr",
            "titulos": ["5x Champions League", "Euro 2016", "5x Bola de Ouro", "3x Premier League"],
            "curiosidade": "Maior artilheiro da história do futebol de seleções"
        },
        {
            "nome": "Neymar",
            "pais": "Brasil",
            "bandeira": "🇧🇷",
            "idade": 34,
            "posicao": "Atacante",
            "principalClube": "Barcelona",
            "clubeAtual": "Santos",
            "titulos": ["Champions League", "2x La Liga", "Ouro Olímpico 2016"],
            "curiosidade": "Maior artilheiro da história da Seleção Brasileira"
        },
        {
            "nome": "Kylian Mbappé",
            "pais": "França",
            "bandeira": "🇫🇷",
            "idade": 27,
            "posicao": "Atacante",
            "principalClube": "PSG",
            "clubeAtual": "Real Madrid",
            "titulos": ["Copa do Mundo 2018", "6x Ligue 1", "La Liga"],
            "curiosidade": "Mais jovem francês a marcar em uma Copa do Mundo"
        },
        {
            "nome": "Erling Haaland",
            "pais": "Noruega",
            "bandeira": "🇳🇴",
            "idade": 25,
            "posicao": "Atacante",
            "primeiroClube": "Bryne",
            "principalClube": "Manchester City",
            "clubeAtual": "Manchester City",
            "titulos": ["Champions League", "2x Premier League", "2x Bundesliga Austríaca"],
            "curiosidade": "Marcou 9 gols em uma única partida"
        },
        {
            "nome": "Martin Ødegaard",
            "pais": "Noruega",
            "bandeira": "🇳🇴",
            "idade": 27,
            "posicao": "Meio-campista",
            "primeiroClube": "Strømsgodset",
            "principalClube": "Arsenal",
            "clubeAtual": "Arsenal",
            "titulos": ["Premier League"],
            "curiosidade": "Marcou 9 gols em uma única partida"
        },
        {
            "nome": "Vinícius Jr",
            "pais": "Brasil",
            "bandeira": "🇧🇷",
            "idade": 25,
            "posicao": "Atacante",
            "principalClube": "Real Madrid",
            "clubeAtual": "Real Madrid",
            "titulos": ["2x Champions League", "3x La Liga", "Bola de Ouro 2024"],
            "curiosidade": "Decisivo em duas finais de Champions League"
        },
        {
            "nome": "Luka Modrić",
            "pais": "Croácia",
            "bandeira": "🇭🇷",
            "idade": 40,
            "posicao": "Meio-campista",
            "principalClube": "Real Madrid",
            "clubeAtual": "Real Madrid",
            "titulos": ["5x Champions League", "Bola de Ouro 2018", "4x La Liga"],
            "curiosidade": "Quebrou a hegemonia Messi-Ronaldo na Bola de Ouro"
        },
        {
            "nome": "Kevin De Bruyne",
            "pais": "Bélgica",
            "bandeira": "🇧🇪",
            "idade": 34,
            "posicao": "Meio-campista",
            "principalClube": "Manchester City",
            "clubeAtual": "Manchester City",
            "titulos": ["Champions League", "6x Premier League"],
            "curiosidade": "Considerado o melhor meio-campista da Premier League"
        },
        {
            "nome": "Karim Benzema",
            "pais": "França",
            "bandeira": "🇫🇷",
            "idade": 38,
            "posicao": "Atacante",
            "principalClube": "Real Madrid",
            "clubeAtual": "Al-Ittihad",
            "titulos": ["5x Champions League", "Bola de Ouro 2022", "4x La Liga"],
            "curiosidade": "Artilheiro histórico do Real Madrid na Champions"
        },
        {
            "nome": "Mohamed Salah",
            "pais": "Egito",
            "bandeira": "🇪🇬",
            "idade": 34,
            "posicao": "Ponta direita",
            "principalClube": "Liverpool",
            "clubeAtual": "Liverpool",
            "titulos": ["Champions League", "2x Premier League", "3x Chuteira de Ouro PL"],
            "curiosidade": "Rei egípcio de Anfield"
        },
        {
            "nome": "Robert Lewandowski",
            "pais": "Polônia",
            "bandeira": "🇵🇱",
            "idade": 37,
            "posicao": "Atacante",
            "principalClube": "Bayern de Munique",
            "clubeAtual": "Barcelona",
            "titulos": ["Champions League", "10x Bundesliga", "2x La Liga"],
            "curiosidade": "Marcou 5 gols em 9 minutos contra o Wolfsburg"
        },
        {
            "nome": "Sadio Mané",
            "pais": "Senegal",
            "bandeira": "🇸🇳",
            "idade": 34,
            "posicao": "Atacante",
            "principalClube": "Liverpool",
            "clubeAtual": "Al-Nassr",
            "titulos": ["Champions League", "Premier League", "Copa Africana 2021", "Bundesliga", "Campeonato Saudita"],
            "curiosidade": "Herói do primeiro título africano do Senegal"
        },
        {
            "nome": "Thibaut Courtois",
            "pais": "Bélgica",
            "bandeira": "🇧🇪",
            "idade": 34,
            "posicao": "Goleiro",
            "principalClube": "Real Madrid",
            "clubeAtual": "Real Madrid",
            "titulos": ["2x Champions League", "3x La Liga"],
            "curiosidade": "Fez 9 defesas na final da Champions 2022"
        },
        {
            "nome": "Virgil van Dijk",
            "pais": "Holanda",
            "bandeira": "🇳🇱",
            "idade": 34,
            "posicao": "Zagueiro",
            "principalClube": "Liverpool",
            "clubeAtual": "Liverpool",
            "titulos": ["Champions League", "Premier League"],
            "curiosidade": "Transformou a defesa do Liverpool ao chegar em 2018"
        },
        {
            "nome": "Jude Bellingham",
            "pais": "Inglaterra",
            "bandeira": "🏴󠁧󠁢󠁥󠁮󠁧󠁿",
            "idade": 22,
            "posicao": "Meio-campista",
            "principalClube": "Real Madrid",
            "clubeAtual": "Real Madrid",
            "titulos": ["Champions League", "La Liga"],
            "curiosidade": "Marcou em sua estreia no clássico contra o Barcelona"
        },
        {
            "nome": "Gianluigi Buffon",
            "pais": "Itália",
            "bandeira": "🇮🇹",
            "idade": 48,
            "posicao": "Goleiro",
            "principalClube": "Juventus",
            "clubeAtual": "Aposentado",
            "titulos": ["Copa do Mundo 2006", "10x Serie A"],
            "curiosidade": "Um dos maiores goleiros da história do futebol"
        },
        {
            "nome": "Ronaldinho",
            "pais": "Brasil",
            "bandeira": "🇧🇷",
            "idade": 46,
            "posicao": "Meio-campista",
            "principalClube": "Barcelona",
            "clubeAtual": "Aposentado",
            "titulos": ["Copa do Mundo 2002", "Champions League", "Bola de Ouro 2005"],
            "curiosidade": "O Bruxo que encantou o Camp Nou de pé"
        },
        {
            "nome": "Zinedine Zidane",
            "pais": "França",
            "bandeira": "🇫🇷",
            "idade": 53,
            "posicao": "Meio-campista",
            "principalClube": "Real Madrid",
            "clubeAtual": "Aposentado",
            "titulos": ["Copa do Mundo 1998", "Champions League", "Bola de Ouro"],
            "curiosidade": "Marcou um dos gols mais bonitos em finais de Champions"
        },
        {
            "nome": "Ronaldo Fenômeno",
            "pais": "Brasil",
            "bandeira": "🇧🇷",
            "idade": 49,
            "posicao": "Atacante",
            "principalClube": "Real Madrid",
            "clubeAtual": "Aposentado",
            "titulos": ["2x Copa do Mundo", "3x Bola de Ouro", "Copa UEFA"],
            "curiosidade": "Marcou 2 gols na final da Copa de 2002"
        },
        {
            "nome": "Thierry Henry",
            "pais": "França",
            "bandeira": "🇫🇷",
            "idade": 48,
            "posicao": "Atacante",
            "principalClube": "Arsenal",
            "clubeAtual": "Aposentado",
            "titulos": ["Copa do Mundo 1998", "Eurocopa", "2x Premier League"],
            "curiosidade": "Maior artilheiro da história do Arsenal"
        },
        {
            "nome": "Kaká",
            "pais": "Brasil",
            "bandeira": "🇧🇷",
            "idade": 44,
            "posicao": "Meio-campista",
            "principalClube": "Milan",
            "clubeAtual": "Aposentado",
            "titulos": ["Copa do Mundo 2002", "Champions League", "Bola de Ouro"],
            "curiosidade": "Último brasileiro a ganhar a Bola de Ouro"
        },
        {
            "nome": "Sergio Ramos",
            "pais": "Espanha",
            "bandeira": "🇪🇸",
            "idade": 40,
            "posicao": "Zagueiro",
            "principalClube": "Real Madrid",
            "clubeAtual": "Aposentado",
            "titulos": ["Copa do Mundo", "4x Champions League", "2x Eurocopa"],
            "curiosidade": "Gol decisivo na final da Champions 2014 (minuto 93)"
        },
        {
            "nome": "Andrés Iniesta",
            "pais": "Espanha",
            "bandeira": "🇪🇸",
            "idade": 42,
            "posicao": "Meio-campista",
            "principalClube": "Barcelona",
            "clubeAtual": "Aposentado",
            "titulos": ["Copa do Mundo 2010", "4x Champions League", "9x La Liga", "2x Eurocopa", "3x Mundial de Clubes"],
            "curiosidade": "Marcou o gol do título na final da Copa do Mundo 2010"
        },
        {
            "nome": "Xavi",
            "pais": "Espanha",
            "bandeira": "🇪🇸",
            "idade": 46,
            "posicao": "Meio-campista",
            "principalClube": "Barcelona",
            "clubeAtual": "Aposentado",
            "titulos": ["Copa do Mundo 2010", "4x Champions League", "8x La Liga"],
            "curiosidade": "Cérebro do tiki-taka do Barcelona e da Espanha"
        },
        {
            "nome": "Andrea Pirlo",
            "pais": "Itália",
            "bandeira": "🇮🇹",
            "idade": 47,
            "posicao": "Meio-campista",
            "principalClube": "Milan",
            "clubeAtual": "Aposentado",
            "titulos": ["Copa do Mundo 2006", "2x Champions League", "6x Serie A"],
            "curiosidade": "Maestro italiano conhecido pela elegância com a bola"
        },
        {
            "nome": "Dani Alves",
            "pais": "Brasil",
            "bandeira": "🇧🇷",
            "idade": 43,
            "posicao": "Lateral",
            "principalClube": "Barcelona",
            "clubeAtual": "Aposentado",
            "titulos": ["3x Champions League", "6x La Liga", "Ouro Olímpico 2020"],
            "curiosidade": "Já foi preso"
        },
        {
            "nome": "Zlatan Ibrahimović",
            "pais": "Suécia",
            "bandeira": "🇸🇪",
            "idade": 44,
            "posicao": "Atacante",
            "principalClube": "Milan",
            "clubeAtual": "Aposentado",
            "titulos": ["13x Liga Nacional", "4x Serie A"],
            "curiosidade": "Jogou em mais de 6 clubes gigantes da Europa"
        },
        {
            "nome": "Marcelo",
            "pais": "Brasil",
            "bandeira": "🇧🇷",
            "idade": 38,
            "posicao": "Lateral",
            "principalClube": "Real Madrid",
            "clubeAtual": "Aposentado",
            "titulos": ["5x Champions League", "6x La Liga", "Libertadores"],
            "curiosidade": "Brasileiro com mais títulos na história do Real Madrid"
        },
        {
            "nome": "Antoine Griezmann",
            "pais": "França",
            "bandeira": "🇫🇷",
            "idade": 35,
            "posicao": "Atacante",
            "principalClube": "Atlético de Madrid",
            "clubeAtual": "Atlético de Madrid",
            "titulos": ["Copa do Mundo 2018", "2x Europa League"],
            "curiosidade": "Famoso pela comemoração do telefone"
        },
        {
            "nome": "Toni Kroos",
            "pais": "Alemanha",
            "bandeira": "🇩🇪",
            "idade": 36,
            "posicao": "Meio-campista",
            "principalClube": "Real Madrid",
            "clubeAtual": "Aposentado",
            "titulos": ["Copa do Mundo", "5x Champions League", "4x La Liga"],
            "curiosidade": "Se aposentou após a Euro 2024 sendo titular absoluto"
        },
        {
            "nome": "Miroslav Klose",
            "pais": "Alemanha",
            "bandeira": "🇩🇪",
            "idade": 48,
            "posicao": "Centroavante",
            "primeiroClube": "Homburg",
            "principalClube": "Bayern de Munique",
            "clubeAtual": "Aposentado",
            "titulos": ["Copa do Mundo", "2x Bundesliga", "Copa"],
            "curiosidade": "Maior artilheiro da história da Copa do Mundo"
        },
        {
            "nome": "Paul Pogba",
            "pais": "França",
            "bandeira": "🇫🇷",
            "idade": 33,
            "posicao": "Meio-campista",
            "principalClube": "Juventus",
            "clubeAtual": "Sem clube",
            "titulos": ["Copa do Mundo 2018", "4x Serie A", "Europa League"],
            "curiosidade": "Meio-campista famoso pelo estilo e penteados únicos"
        },
        {
            "nome": "N'Golo Kanté",
            "pais": "França",
            "bandeira": "🇫🇷",
            "idade": 35,
            "posicao": "Meio-campista",
            "principalClube": "Chelsea",
            "clubeAtual": "Al-Ittihad",
            "titulos": ["Copa do Mundo 2018", "Champions League", "2x Premier League"],
            "curiosidade": "Cobertura de campo comparada a dois jogadores"
        },
        {
            "nome": "Manuel Neuer",
            "pais": "Alemanha",
            "bandeira": "🇩🇪",
            "idade": 40,
            "posicao": "Goleiro",
            "principalClube": "Bayern de Munique",
            "clubeAtual": "Bayern de Munique",
            "titulos": ["Copa do Mundo 2014", "2x Champions League", "12x Bundesliga"],
            "curiosidade": "Revolucionou a posição de goleiro com seu estilo líbero"
        },
        {
            "nome": "Luis Suárez",
            "pais": "Uruguai",
            "bandeira": "🇺🇾",
            "idade": 39,
            "posicao": "Atacante",
            "principalClube": "Barcelona",
            "clubeAtual": "Aposentado",
            "titulos": ["Champions League", "4x La Liga", "Chuteira de Ouro"],
            "curiosidade": "Formou o trio MSN com Messi e Neymar"
        },
        {
            "nome": "Sergio Agüero",
            "pais": "Argentina",
            "bandeira": "🇦🇷",
            "idade": 38,
            "posicao": "Atacante",
            "principalClube": "Manchester City",
            "clubeAtual": "Aposentado",
            "titulos": ["5x Premier League"],
            "curiosidade": "Gol mais icônico da Premier League (93:20)"
        },
        {
            "nome": "Wayne Rooney",
            "pais": "Inglaterra",
            "bandeira": "🏴󠁧󠁢󠁥󠁮󠁧󠁿",
            "idade": 40,
            "posicao": "Atacante",
            "principalClube": "Manchester United",
            "clubeAtual": "Aposentado",
            "titulos": ["Champions League", "5x Premier League"],
            "curiosidade": "Maior artilheiro da história do Manchester United"
        },
        {
            "nome": "Thiago Silva",
            "pais": "Brasil",
            "bandeira": "🇧🇷",
            "idade": 41,
            "posicao": "Zagueiro",
            "principalClube": "Paris Saint-Germain",
            "clubeAtual": "Fluminense",
            "titulos": ["Champions League (vice)", "8x Ligue 1", "Copa América 2019"],
            "curiosidade": "Capitão do PSG e do Chelsea em finais europeias"
        },
        {
            "nome": "Casemiro",
            "pais": "Brasil",
            "bandeira": "🇧🇷",
            "idade": 34,
            "posicao": "Meio-campista",
            "principalClube": "Real Madrid",
            "clubeAtual": "Manchester United",
            "titulos": ["5x Champions League", "3x La Liga"],
            "curiosidade": "Pilar defensivo do meio-campo do Real Madrid por quase uma década"
        },
        {
            "nome": "Pedri",
            "pais": "Espanha",
            "bandeira": "🇪🇸",
            "idade": 23,
            "posicao": "Meio-campista",
            "principalClube": "Barcelona",
            "clubeAtual": "Barcelona",
            "titulos": ["La Liga", "Golden Boy 2021", "Troféu Kopa"],
            "curiosidade": "Com 18 anos já era titular do Barça e da Espanha na Euro"
        },
        {
            "nome": "Lamine Yamal",
            "pais": "Espanha",
            "bandeira": "🇪🇸",
            "idade": 18,
            "posicao": "Atacante",
            "principalClube": "Barcelona",
            "clubeAtual": "Barcelona",
            "titulos": ["Euro 2024", "La Liga"],
            "curiosidade": "Mais jovem a jogar e marcar na história da Eurocopa"
        },
        {
            "nome": "Rodri",
            "pais": "Espanha",
            "bandeira": "🇪🇸",
            "idade": 30,
            "posicao": "Volante",
            "principalClube": "Manchester City",
            "clubeAtual": "Manchester City",
            "titulos": ["Champions League", "Euro 2024", "Bola de Ouro 2024", "4x Premier League"],
            "curiosidade": "Teve uma sequência de 74 jogos invicto"
        },
        {
            "nome": "Eden Hazard",
            "pais": "Bélgica",
            "bandeira": "🇧🇪",
            "idade": 35,
            "posicao": "Ponta-esquerda",
            "primeiroClube": "Lille",
            "principalClube": "Chelsea",
            "clubeAtual": "Aposentado",
            "titulos": ["Champions League", "2x Europa League", "2x La Liga", "2x Premier League"],
            "curiosidade": "Teve uma sequência de 74 jogos invicto"
        },
        {
            "nome": "Alisson",
            "pais": "Brasil",
            "bandeira": "🇧🇷",
            "idade": 33,
            "posicao": "Goleiro",
            "primeiroClube": "Internacional",
            "principalClube": "Liverpool",
            "clubeAtual": "Liverpool",
            "titulos": ["Champions League", "Copa América 2019", "4x Campeonato Gaúcho", "2x Premier League"],
            "curiosidade": "Teve uma sequência de 74 jogos invicto"
        },
        {
            "nome": "Joe Gomez",
            "pais": "Inglaterra",
            "bandeira": "🏴󠁧󠁢󠁥󠁮󠁧󠁿",
            "idade": 29,
            "posicao": "Zagueiro",
            "primeiroClube": "Charlton Athletic",
            "principalClube": "Liverpool",
            "clubeAtual": "Liverpool",
            "titulos": ["Champions League", "2x Premier League", "Copa do Mundo de Clubes 2019"],
            "curiosidade": "Teve uma sequência de 74 jogos invicto"
        },
        {
            "nome": "Milos Kerkez",
            "pais": "Hungria",
            "bandeira": "🇭🇺",
            "idade": 22,
            "posicao": "Lateral esquerdo",
            "primeiroClube": "Győri",
            "principalClube": "Liverpool",
            "clubeAtual": "Liverpool",
            "titulos": ["Não tem títulos"],
            "curiosidade": "Nasceu na Sérvia mas joga pela Seleção Húngara"
        },
        {
            "nome": "Florian Wirtz",
            "pais": "Alemanha",
            "bandeira": "🇩🇪",
            "idade": 23,
            "posicao": "Meio-campista",
            "primeiroClube": "Bayer Leverkusen",
            "principalClube": "Liverpool",
            "clubeAtual": "Liverpool",
            "titulos": ["Bundesliga", "Eurocopa Sub-21"],
            "curiosidade": "Sua irmã é jogadora de futebol"
        },
        {
            "nome": "Dominik Szoboszlai",
            "pais": "Hungria",
            "bandeira": "🇭🇺",
            "idade": 25,
            "posicao": "Meio-campista",
            "primeiroClube": "Liefering",
            "principalClube": "Liverpool",
            "clubeAtual": "Liverpool",
            "titulos": ["2x Bundesliga Austríaca", "Premier League"],
            "curiosidade": "Tem uma tatuagem no braço com uma frase de Gerrard"
        },
        {
            "nome": "Alexander Isak",
            "pais": "Suécia",
            "bandeira": "🇸🇪",
            "idade": 26,
            "posicao": "Centroavante",
            "primeiroClube": "AIK",
            "principalClube": "Liverpool",
            "clubeAtual": "Liverpool",
            "titulos": ["Copa da Alemanha", "Copa do Rei", "Copa da Liga Inglesa"],
            "curiosidade": "Contratação mais cara do Liverpool"
        },
        {
            "nome": "Alexander Isak",
            "pais": "Suécia",
            "bandeira": "🇸🇪",
            "idade": 26,
            "posicao": "Centroavante",
            "primeiroClube": "AIK",
            "principalClube": "Liverpool",
            "clubeAtual": "Liverpool",
            "titulos": ["Copa da Alemanha", "Copa do Rei", "Copa da Liga Inglesa"],
            "curiosidade": "Contratação mais cara do Liverpool"
        },
        {
            "nome": "Alexis Mac Allister",
            "pais": "Argentina",
            "bandeira": "🇦🇷",
            "idade": 27,
            "posicao": "Meio-campista",
            "primeiroClube": "Argentinos Juniors",
            "principalClube": "Liverpool",
            "clubeAtual": "Liverpool",
            "titulos": ["Campeonato Argentino", "Premier League", "Finalíssima", "Copa do Mundo 2022", "Copa América 2024"],
            "curiosidade": "Seu nome é descendente de irlandeses e escoceses"
        },
        {
            "nome": "Federico Chiesa",
            "pais": "Itália",
            "bandeira": "🇮🇹",
            "idade": 28,
            "posicao": "Ponta-direita",
            "primeiroClube": "Fiorentina",
            "principalClube": "Juventus",
            "clubeAtual": "Liverpool",
            "titulos": ["2x Copa da Itália", "Premier League", "Eurocopa"],
            "curiosidade": "Se destacou na Juventus e na Seleção Italiana disputanto a Eurocopa de 2020"
        },
        {
            "nome": "Cody Gakpo",
            "pais": "Holanda",
            "bandeira": "🇳🇱",
            "idade": 27,
            "posicao": "Ponta-esquerda",
            "primeiroClube": "PSV Eindhoven",
            "principalClube": "Liverpool",
            "clubeAtual": "Liverpool",
            "titulos": ["Eredivisie", "Premier League"],
            "curiosidade": "Maior venda da história do PSV"
        },
        {
            "nome": "Hugo Ekitike",
            "pais": "França",
            "bandeira": "🇫🇷",
            "idade": 23,
            "posicao": "Centroavante",
            "primeiroClube": "Reims",
            "principalClube": "Liverpool",
            "clubeAtual": "Liverpool",
            "titulos": ["Ligue 1"],
            "curiosidade": "Maior venda da história do Frankfurt"
        },
        {
            "nome": "Jeremie Frimpong",
            "pais": "Holanda",
            "bandeira": "🇳🇱",
            "idade": 25,
            "posicao": "Lateral direito",
            "primeiroClube": "Celtic",
            "principalClube": "Liverpool",
            "clubeAtual": "Liverpool",
            "titulos": ["Scottish Premiership", "Bundesliga"],
            "curiosidade": "Passou 9 anos na base do Manchester City"
        },
        {
            "nome": "Ryan Gravenberch",
            "pais": "Holanda",
            "bandeira": "🇳🇱",
            "idade": 24,
            "posicao": "Volante",
            "primeiroClube": "Ajax",
            "principalClube": "Liverpool",
            "clubeAtual": "Liverpool",
            "titulos": ["Eredivisie", "Bundesliga", "Premier League", "Campeonato Europeu Sub-17"],
            "curiosidade": "Jogador mais jovem a marcar gol pelo Ajax"
        },
        {
            "nome": "Robert Sánchez",
            "pais": "Espanha",
            "bandeira": "🇪🇸",
            "idade": 28,
            "posicao": "Goleiro",
            "primeiroClube": "Brigton & Hove Albion",
            "principalClube": "Chelsea",
            "clubeAtual": "Chelsea",
            "titulos": ["Conference League", "Super Mundial de Clubes 2025"],
            "curiosidade": "Melhor goleiro do Super Mundial de Clubes"
        },
        {
            "nome": "Marc Cucurella",
            "pais": "Espanha",
            "bandeira": "🇪🇸",
            "idade": 27,
            "posicao": "Lateral esquerdo",
            "primeiroClube": "Barcelona",
            "principalClube": "Chelsea",
            "clubeAtual": "Chelsea",
            "titulos": ["Copa do Rei", "Conference League", "Super Mundial de Clubes 2025", "Eurocopa"],
            "curiosidade": "Lateral mais chato do futebol e famoso pela sua cabeleira"
        },
        {
            "nome": "Tosin Adarabioyo",
            "pais": "Inglaterra",
            "bandeira": "🏴󠁧󠁢󠁥󠁮󠁧󠁿",
            "idade": 28,
            "posicao": "Zagueiro",
            "primeiroClube": "Manchester City",
            "principalClube": "Chelsea",
            "clubeAtual": "Chelsea",
            "titulos": ["Premier League", "Conference League", "Super Mundial de Clubes 2025", "Championship"],
            "curiosidade": "Jogador nascido na Nigéria e naturalizado inglês"
        },
        {
            "nome": "Pedro Neto",
            "pais": "Portugal",
            "bandeira": "🇵🇹",
            "idade": 26,
            "posicao": "Ponta-esquerda",
            "primeiroClube": "Braga",
            "principalClube": "Chelsea",
            "clubeAtual": "Chelsea",
            "titulos": ["Copa da Itália", "Conference League", "Super Mundial de Clubes 2025", "Nations League"],
            "curiosidade": "Jogador 'revelado' por Abel Ferreira"
        },
        {
            "nome": "Enzo Fernández",
            "pais": "Argentina",
            "bandeira": "🇦🇷",
            "idade": 25,
            "posicao": "Meio-campista",
            "primeiroClube": "River Plate",
            "principalClube": "Chelsea",
            "clubeAtual": "Chelsea",
            "titulos": ["Copa Sul-Americana", "Conference League", "Super Mundial de Clubes 2025", "Campeonato Argentino", "Primeira Liga", "Copa do Mundo", "Copa América"],
            "curiosidade": "Melhor jogador jovem da Copa do Mundo de 2022"
        },
        {
            "nome": "Enzo Fernández",
            "pais": "Argentina",
            "bandeira": "🇦🇷",
            "idade": 25,
            "posicao": "Meio-campista",
            "primeiroClube": "River Plate",
            "principalClube": "Chelsea",
            "clubeAtual": "Chelsea",
            "titulos": ["Copa Sul-Americana", "Conference League", "Super Mundial de Clubes 2025", "Campeonato Argentino", "Primeira Liga", "Copa do Mundo", "Copa América"],
            "curiosidade": "Melhor jogador jovem da Copa do Mundo de 2022"
        },
        {
            "nome": "Cole Palmer",
            "pais": "Inglaterra",
            "bandeira": "🏴󠁧󠁢󠁥󠁮󠁧󠁿",
            "idade": 24,
            "posicao": "Meio-campista",
            "primeiroClube": "Manchester City",
            "principalClube": "Chelsea",
            "clubeAtual": "Chelsea",
            "titulos": ["Premier League", "Conference League", "Super Mundial de Clubes 2025", "Champions League"],
            "curiosidade": "Jogador da comemoração fria"
        },
        {
            "nome": "Andrey Santos",
            "pais": "Brasil",
            "bandeira": "🇧🇷",
            "idade": 22,
            "posicao": "Volante",
            "primeiroClube": "Vasco da Gama",
            "principalClube": "Chelsea",
            "clubeAtual": "Chelsea",
            "titulos": ["Taça Rio", "Super Mundial de Clubes 2025"],
            "curiosidade": "Passou por 3 empréstimos até se firmar no Chelsea"
        },
        {
            "nome": "João Pedro",
            "pais": "Brasil",
            "bandeira": "🇧🇷",
            "idade": 24,
            "posicao": "Centroavante",
            "primeiroClube": "Fluminense",
            "principalClube": "Chelsea",
            "clubeAtual": "Chelsea",
            "titulos": ["Super Mundial de Clubes 2025"],
            "curiosidade": "Ex namorado da atriz Mel Maia"
        },
        {
            "nome": "Reece James",
            "pais": "Inglaterra",
            "bandeira": "🏴󠁧󠁢󠁥󠁮󠁧󠁿",
            "idade": 26,
            "posicao": "Lateral direito",
            "primeiroClube": "Chelsea",
            "principalClube": "Chelsea",
            "clubeAtual": "Chelsea",
            "titulos": ["Champions League", "Mundial de Clubes", "Conference League", "Super Mundial de Clubes 2025"],
            "curiosidade": "Está no Chelsea desde os 6 anos de idade"
        },
        {
            "nome": "Moisés Caicedo",
            "pais": "Equador",
            "bandeira": "🇪🇨",
            "idade": 24,
            "posicao": "Volante",
            "primeiroClube": "Independiente del Valle",
            "principalClube": "Chelsea",
            "clubeAtual": "Chelsea",
            "titulos": ["Conference League", "Super Mundial de Clubes 2025"],
            "curiosidade": "Maior contratação da história do Chelsea"
        }
    ]
} 
