{
    "Brasil": {
        "1958": {
            "tecnico": "Vicente Feola",
            "jogadores": {
                "goleiro": ["Castilho", "Gilmar"],
                "zagueiro": ["Bellini", "Zózimo", "Orlando", "Mauro"],
                "lateral": ["Djalma Santos", "Oreco", "Nilton Santos", "De Sordi"],
                "meioCampo": ["Dino Sani", "Didi", "Zito", "Moacir"],
                "atacante": ["Zagallo", "Pelé", "Garrincha", "Joel", "Mazzola", "Vavá", "Dida", "Pepe"]
            }
        },
        "1962": {
            "tecnico": "Aymoré Moreira",
            "jogadores": {
                "goleiro": ["Castilho", "Gylmar", "Valdir", "Laércio"],
                "zagueiro": ["Bellini", "Zózimo", "Orlando", "Mauro"],
                "lateral": ["Djalma Santos", "Oreco", "Nilton Santos", "De Sordi"],
                "meioCampo": ["Dino Sani", "Didi", "Zito", "Moacir"],
                "atacante": ["Zagallo", "Pelé", "Garrincha", "Joel", "Mazzola", "Vavá", "Dida", "Pepe"]
            }
        }
    }
}